google_flight_analysis/__init__.py
google_flight_analysis/analysis.py
google_flight_analysis/cache.py
google_flight_analysis/flight.py
google_flight_analysis/scrape.py
google_flight_analysis-1.2.0.dist-info/LICENSE
google_flight_analysis-1.2.0.dist-info/METADATA
google_flight_analysis-1.2.0.dist-info/WHEEL
google_flight_analysis-1.2.0.dist-info/entry_points.txt
google_flight_analysis-1.2.0.dist-info/top_level.txt
google_flight_analysis-1.2.0.dist-info/RECORD
