Metadata-Version: 2.1
Name: google-flight-analysis
Version: 1.2.0
Summary: Scraping flight data from Google Flights and analyzing.
Home-page: https://github.com/kcelebi/flight_analysis
Author: Kaya Celebi
Author-email: kayacelebi17@gmail.com
Project-URL: Bug Tracker, https://github.com/kcelebi/flight_analysis/issues
Project-URL: Changelog, https://github.com/kcelebi/flight_analysis/releases
Classifier: Programming Language :: Python :: 3
Classifier: License :: OSI Approved :: MIT License
Classifier: Intended Audience :: Developers
Requires-Python: >=3.6
License-File: LICENSE
